README.md
setup.py
heartrate/__init__.py
heartrate/core.py
heartrate/files.py
heartrate.egg-info/PKG-INFO
heartrate.egg-info/SOURCES.txt
heartrate.egg-info/dependency_links.txt
heartrate.egg-info/not-zip-safe
heartrate.egg-info/requires.txt
heartrate.egg-info/top_level.txt
heartrate/static/favicon.ico
heartrate/static/css/bootstrap.min.css
heartrate/static/css/main.css
heartrate/static/css/monokai.css
heartrate/static/fonts/glyphicons-halflings-regular.eot
heartrate/static/fonts/glyphicons-halflings-regular.svg
heartrate/static/fonts/glyphicons-halflings-regular.ttf
heartrate/static/fonts/glyphicons-halflings-regular.woff
heartrate/static/fonts/glyphicons-halflings-regular.woff2
heartrate/static/img/logo.png
heartrate/static/img/logo_full.png
heartrate/static/js/stacktrace.js
heartrate/static/js/libs/jquery-3.2.1.js
heartrate/templates/base.html
heartrate/templates/file.html
heartrate/templates/file_table.html
heartrate/templates/index.html